{
  "ground_state_scalars": {
    "dft_dipole_magnitude_debye": {
      "smd": -0.04099382664055094,
      "spearman_acceptor_similarity": 0.11263771988286608,
      "spearman_c0_abs_error": 0.050774070570800287,
      "spearman_c0_residual": -0.07855016295044448,
      "train_identity_mean": 5.695081587063814,
      "train_identity_n": 284,
      "train_n": 10543,
      "val_identities_with_any_missing": 0,
      "val_identity_mean": 5.491351085488375,
      "val_identity_n": 32,
      "val_n": 2235,
      "wasserstein": 0.32426080947715774
    },
    "dft_gap_hartree": {
      "smd": 0.4224521731125351,
      "spearman_acceptor_similarity": -0.03929680057859251,
      "spearman_c0_abs_error": -0.10725006433716984,
      "spearman_c0_residual": 0.14116184641263502,
      "train_identity_mean": 0.07772602529008708,
      "train_identity_n": 284,
      "train_n": 10543,
      "val_identities_with_any_missing": 0,
      "val_identity_mean": 0.0878695711209804,
      "val_identity_n": 32,
      "val_n": 2235,
      "wasserstein": 0.010785524324058222
    },
    "dft_homo_hartree": {
      "smd": -0.3768588647589725,
      "spearman_acceptor_similarity": 0.05440643622258906,
      "spearman_c0_abs_error": -0.044870884869621125,
      "spearman_c0_residual": 0.11075609189449541,
      "train_identity_mean": -0.19205392950988667,
      "train_identity_n": 284,
      "train_n": 10543,
      "val_identities_with_any_missing": 0,
      "val_identity_mean": -0.19665575376803712,
      "val_identity_n": 32,
      "val_n": 2235,
      "wasserstein": 0.003473954084275305
    },
    "dft_lumo_hartree": {
      "smd": 0.22952447249786442,
      "spearman_acceptor_similarity": -0.0429402233524632,
      "spearman_c0_abs_error": -0.13351386711350863,
      "spearman_c0_residual": 0.17938273779132605,
      "train_identity_mean": -0.11432790421979958,
      "train_identity_n": 284,
      "train_n": 10543,
      "val_identities_with_any_missing": 0,
      "val_identity_mean": -0.10878618264705672,
      "val_identity_n": 32,
      "val_n": 2235,
      "wasserstein": 0.010746487196674703
    },
    "electron_count": {
      "smd": -0.4745799719077888,
      "spearman_acceptor_similarity": 0.05467530413983411,
      "spearman_c0_abs_error": -0.007872257867822656,
      "spearman_c0_residual": -0.024765837537099097,
      "train_identity_mean": 1018.5750047613991,
      "train_identity_n": 284,
      "train_n": 10543,
      "val_identities_with_any_missing": 0,
      "val_identity_mean": 868.8910712164557,
      "val_identity_n": 32,
      "val_n": 2235,
      "wasserstein": 116.3514671036117
    },
    "formal_charge": {
      "smd": null,
      "spearman_acceptor_similarity": null,
      "spearman_c0_abs_error": null,
      "spearman_c0_residual": null,
      "train_identity_mean": 0.0,
      "train_identity_n": 284,
      "train_n": 10543,
      "val_identities_with_any_missing": 0,
      "val_identity_mean": 0.0,
      "val_identity_n": 32,
      "val_n": 2235,
      "wasserstein": 0.0
    },
    "identity_power": {
      "train_acceptor_identities": 284,
      "validation_acceptor_identities": 32
    },
    "pm6_dipole_magnitude_debye": {
      "smd": 0.02404776832851912,
      "spearman_acceptor_similarity": 0.16138835106261454,
      "spearman_c0_abs_error": 0.008139133026784066,
      "spearman_c0_residual": -0.017834741281405882,
      "train_identity_mean": 5.563132207502967,
      "train_identity_n": 284,
      "train_n": 10543,
      "val_identities_with_any_missing": 0,
      "val_identity_mean": 5.636804401920057,
      "val_identity_n": 32,
      "val_n": 2235,
      "wasserstein": 0.17868819420882326
    },
    "pm6_gap_hartree": {
      "smd": 0.3503756550290402,
      "spearman_acceptor_similarity": -0.07128068568924005,
      "spearman_c0_abs_error": -0.11502944214233099,
      "spearman_c0_residual": 0.11831397784650875,
      "train_identity_mean": 0.22171581296689488,
      "train_identity_n": 284,
      "train_n": 10543,
      "val_identities_with_any_missing": 0,
      "val_identity_mean": 0.23014150011840423,
      "val_identity_n": 32,
      "val_n": 2235,
      "wasserstein": 0.006872103516843028
    },
    "pm6_homo_hartree": {
      "smd": -0.3372125773285873,
      "spearman_acceptor_similarity": -0.013004911687647298,
      "spearman_c0_abs_error": 0.005836996605473914,
      "spearman_c0_residual": 0.07119777309634198,
      "train_identity_mean": -0.3033618213590411,
      "train_identity_n": 284,
      "train_n": 10543,
      "val_identities_with_any_missing": 0,
      "val_identity_mean": -0.30800588900587955,
      "val_identity_n": 32,
      "val_n": 2235,
      "wasserstein": 0.0034588108581008713
    },
    "pm6_lumo_hartree": {
      "smd": 0.16699447808798043,
      "spearman_acceptor_similarity": -0.11804978151002776,
      "spearman_c0_abs_error": -0.13236799829756055,
      "spearman_c0_residual": 0.16089709482868836,
      "train_identity_mean": -0.0816460083921462,
      "train_identity_n": 284,
      "train_n": 10543,
      "val_identities_with_any_missing": 0,
      "val_identity_mean": -0.07786438888747532,
      "val_identity_n": 32,
      "val_n": 2235,
      "wasserstein": 0.005187370076013411
    }
  },
  "pm6_dft_deltas": {
    "abs_delta_dipole_magnitude_debye": {
      "smd": 0.013663821472256414,
      "spearman_acceptor_similarity": 0.026833327957653866,
      "spearman_c0_abs_error": -0.020108177889141116,
      "spearman_c0_residual": -0.013574234537259384,
      "train_identity_mean": 1.0503443196876607,
      "train_identity_n": 284,
      "train_n": 10543,
      "val_identities_with_any_missing": 0,
      "val_identity_mean": 1.0692856852059933,
      "val_identity_n": 32,
      "val_n": 2235,
      "wasserstein": 0.02047207147632976
    },
    "abs_delta_gap_hartree": {
      "smd": -0.13809795311009018,
      "spearman_acceptor_similarity": -0.18039915934610026,
      "spearman_c0_abs_error": 0.01081751224173589,
      "spearman_c0_residual": -0.10069595734195502,
      "train_identity_mean": 0.1439897876768078,
      "train_identity_n": 284,
      "train_n": 10543,
      "val_identities_with_any_missing": 0,
      "val_identity_mean": 0.14227192899742386,
      "val_identity_n": 32,
      "val_n": 2235,
      "wasserstein": 0.0019634739438214154
    },
    "abs_delta_homo_hartree": {
      "smd": -0.002868267587186754,
      "spearman_acceptor_similarity": 0.1202817549346577,
      "spearman_c0_abs_error": -0.08665620891168582,
      "spearman_c0_residual": 0.04498550321839159,
      "train_identity_mean": 0.11130789184915442,
      "train_identity_n": 284,
      "train_n": 10543,
      "val_identities_with_any_missing": 0,
      "val_identity_mean": 0.11135013523784246,
      "val_identity_n": 32,
      "val_n": 2235,
      "wasserstein": 0.0002939925049668751
    },
    "abs_delta_lumo_hartree": {
      "smd": -0.15452814582988644,
      "spearman_acceptor_similarity": -0.25418689877945716,
      "spearman_c0_abs_error": 0.0510630894335197,
      "spearman_c0_residual": -0.13834993649808783,
      "train_identity_mean": 0.03272731767141973,
      "train_identity_n": 284,
      "train_n": 10543,
      "val_identities_with_any_missing": 0,
      "val_identity_mean": 0.030933135972696136,
      "val_identity_n": 32,
      "val_n": 2235,
      "wasserstein": 0.0023415716041751676
    },
    "delta_dipole_magnitude_debye": {
      "smd": -0.14481641185686936,
      "spearman_acceptor_similarity": -0.06388237676614296,
      "spearman_c0_abs_error": 0.08909629722099564,
      "spearman_c0_residual": -0.10007866421479154,
      "train_identity_mean": 0.13194937956084699,
      "train_identity_n": 284,
      "train_n": 10543,
      "val_identities_with_any_missing": 0,
      "val_identity_mean": -0.1454533164316818,
      "val_identity_n": 32,
      "val_n": 2235,
      "wasserstein": 0.19991162592481082
    },
    "delta_gap_hartree": {
      "smd": 0.13809795311009018,
      "spearman_acceptor_similarity": 0.18039915934610026,
      "spearman_c0_abs_error": -0.01081751224173589,
      "spearman_c0_residual": 0.10069595734195502,
      "train_identity_mean": -0.1439897876768078,
      "train_identity_n": 284,
      "train_n": 10543,
      "val_identities_with_any_missing": 0,
      "val_identity_mean": -0.14227192899742386,
      "val_identity_n": 32,
      "val_n": 2235,
      "wasserstein": 0.001963473943821415
    },
    "delta_homo_hartree": {
      "smd": -0.002868267587186754,
      "spearman_acceptor_similarity": 0.1202817549346577,
      "spearman_c0_abs_error": -0.08665620891168582,
      "spearman_c0_residual": 0.04498550321839159,
      "train_identity_mean": 0.11130789184915442,
      "train_identity_n": 284,
      "train_n": 10543,
      "val_identities_with_any_missing": 0,
      "val_identity_mean": 0.11135013523784246,
      "val_identity_n": 32,
      "val_n": 2235,
      "wasserstein": 0.0002939925049668751
    },
    "delta_lumo_hartree": {
      "smd": 0.150555859871116,
      "spearman_acceptor_similarity": 0.25417231801479284,
      "spearman_c0_abs_error": -0.05103821197621852,
      "spearman_c0_residual": 0.13832471723774403,
      "train_identity_mean": -0.03268189582765339,
      "train_identity_n": 284,
      "train_n": 10543,
      "val_identities_with_any_missing": 0,
      "val_identity_mean": -0.03092179375958138,
      "val_identity_n": 32,
      "val_n": 2235,
      "wasserstein": 0.0023691601331799613
    },
    "identity_power": {
      "train_acceptor_identities": 284,
      "validation_acceptor_identities": 32
    }
  },
  "role_counts": {
    "acceptor_atom_count": {
      "smd": -1.3797045593734307,
      "spearman_acceptor_similarity": 0.574573300352065,
      "spearman_c0_abs_error": -0.03916515085779001,
      "spearman_c0_residual": 0.06226800132479442,
      "train_identity_mean": 170.522257768843,
      "train_identity_n": 284,
      "train_n": 10543,
      "val_identities_with_any_missing": 0,
      "val_identity_mean": 53.33264947084484,
      "val_identity_n": 32,
      "val_n": 2235,
      "wasserstein": 90.88036011467685
    },
    "acceptor_atom_fraction": {
      "smd": -1.2689059321669123,
      "spearman_acceptor_similarity": 0.5022620072133379,
      "spearman_c0_abs_error": -0.02062391019241878,
      "spearman_c0_residual": 0.06301362563906064,
      "train_identity_mean": 0.6673343514019973,
      "train_identity_n": 284,
      "train_n": 10543,
      "val_identities_with_any_missing": 0,
      "val_identity_mean": 0.24089507904072704,
      "val_identity_n": 32,
      "val_n": 2235,
      "wasserstein": 0.34632874799789026
    },
    "acceptor_present": {
      "smd": null,
      "spearman_acceptor_similarity": null,
      "spearman_c0_abs_error": null,
      "spearman_c0_residual": null,
      "train_identity_mean": 1.0,
      "train_identity_n": 284,
      "train_n": 10543,
      "val_identities_with_any_missing": 0,
      "val_identity_mean": 1.0,
      "val_identity_n": 32,
      "val_n": 2235,
      "wasserstein": 0.0
    },
    "donor_atom_count": {
      "smd": 0.8625184769776362,
      "spearman_acceptor_similarity": -0.19842220064057714,
      "spearman_c0_abs_error": 0.013356374103829255,
      "spearman_c0_residual": -0.017325716126657488,
      "train_identity_mean": 85.51084378885443,
      "train_identity_n": 284,
      "train_n": 10543,
      "val_identities_with_any_missing": 0,
      "val_identity_mean": 164.6822210488228,
      "val_identity_n": 32,
      "val_n": 2235,
      "wasserstein": 62.31442981666005
    },
    "donor_atom_fraction": {
      "smd": 1.2616447354444602,
      "spearman_acceptor_similarity": -0.49775772823024383,
      "spearman_c0_abs_error": 0.02245119511911777,
      "spearman_c0_residual": -0.06749880784753434,
      "train_identity_mean": 0.3268385717888932,
      "train_identity_n": 284,
      "train_n": 10543,
      "val_identities_with_any_missing": 0,
      "val_identity_mean": 0.7568104270453042,
      "val_identity_n": 32,
      "val_n": 2235,
      "wasserstein": 0.3497113646752411
    },
    "donor_present": {
      "smd": 0.2048354810985293,
      "spearman_acceptor_similarity": -0.10745926945018833,
      "spearman_c0_abs_error": 0.03833823745382398,
      "spearman_c0_residual": -0.00551727727392091,
      "train_identity_mean": 0.9530179075641136,
      "train_identity_n": 284,
      "train_n": 10543,
      "val_identities_with_any_missing": 0,
      "val_identity_mean": 0.9876764648600269,
      "val_identity_n": 32,
      "val_n": 2235,
      "wasserstein": 0.028613872962138007
    },
    "identity_power": {
      "train_acceptor_identities": 284,
      "validation_acceptor_identities": 32
    },
    "unknown_atom_count": {
      "smd": -0.1862591250099762,
      "spearman_acceptor_similarity": 0.10035296803762968,
      "spearman_c0_abs_error": -0.04548469793672664,
      "spearman_c0_residual": 0.044564887425311665,
      "train_identity_mean": 1.2937847339304744,
      "train_identity_n": 284,
      "train_n": 10543,
      "val_identities_with_any_missing": 0,
      "val_identity_mean": 0.45459238446619155,
      "val_identity_n": 32,
      "val_n": 2235,
      "wasserstein": 0.754946622131884
    },
    "unknown_atom_fraction": {
      "smd": -0.16521280216780915,
      "spearman_acceptor_similarity": 0.10035861702219773,
      "spearman_c0_abs_error": -0.04554010918517756,
      "spearman_c0_residual": 0.04455471342954874,
      "train_identity_mean": 0.005827076809109412,
      "train_identity_n": 284,
      "train_n": 10543,
      "val_identities_with_any_missing": 0,
      "val_identity_mean": 0.0022944939139688094,
      "val_identity_n": 32,
      "val_n": 2235,
      "wasserstein": 0.0033925806461869113
    },
    "unknown_present": {
      "smd": -0.24013179208586985,
      "spearman_acceptor_similarity": 0.10059966172516353,
      "spearman_c0_abs_error": -0.04561205199783858,
      "spearman_c0_residual": 0.04453234641914579,
      "train_identity_mean": 0.0811849495041824,
      "train_identity_n": 284,
      "train_n": 10543,
      "val_identities_with_any_missing": 0,
      "val_identity_mean": 0.02660267357164666,
      "val_identity_n": 32,
      "val_n": 2235,
      "wasserstein": 0.046303695890335894
    }
  },
  "role_interface_geometry": {
    "acceptor_interface_atoms_4A": {
      "smd": -0.3628715714016961,
      "spearman_acceptor_similarity": -0.11106838502790335,
      "spearman_c0_abs_error": 0.05167364283177103,
      "spearman_c0_residual": -0.025543568476994294,
      "train_identity_mean": 7.801033548195737,
      "train_identity_n": 284,
      "train_n": 10180,
      "val_identities_with_any_missing": 8,
      "val_identity_mean": 6.703304157755193,
      "val_identity_n": 32,
      "val_n": 2222,
      "wasserstein": 0.8516156527244084
    },
    "da_centroid_distance": {
      "smd": -0.15934226426110856,
      "spearman_acceptor_similarity": -0.010783608082844216,
      "spearman_c0_abs_error": -0.003519732308528627,
      "spearman_c0_residual": -0.049141098343146436,
      "train_identity_mean": 13.882518306707011,
      "train_identity_n": 284,
      "train_n": 10180,
      "val_identities_with_any_missing": 8,
      "val_identity_mean": 12.973718916953013,
      "val_identity_n": 32,
      "val_n": 2222,
      "wasserstein": 0.9467813099474243
    },
    "da_contacts_le_3.5A": {
      "smd": -0.20918204487297262,
      "spearman_acceptor_similarity": -0.054813394782876876,
      "spearman_c0_abs_error": 0.021898199329027063,
      "spearman_c0_residual": -0.06390541645661979,
      "train_identity_mean": 12.3263668896111,
      "train_identity_n": 284,
      "train_n": 10180,
      "val_identities_with_any_missing": 8,
      "val_identity_mean": 11.414634838468034,
      "val_identity_n": 32,
      "val_n": 2222,
      "wasserstein": 0.8592600517419127
    },
    "da_contacts_le_4A": {
      "smd": -0.25936463009454164,
      "spearman_acceptor_similarity": -0.054530575368750875,
      "spearman_c0_abs_error": 0.03936332484404563,
      "spearman_c0_residual": -0.07091533137364003,
      "train_identity_mean": 22.814326690226185,
      "train_identity_n": 284,
      "train_n": 10180,
      "val_identities_with_any_missing": 8,
      "val_identity_mean": 20.02000897153741,
      "val_identity_n": 32,
      "val_n": 2222,
      "wasserstein": 2.2261496483636583
    },
    "da_contacts_le_5A": {
      "smd": -0.3101913775034368,
      "spearman_acceptor_similarity": 0.022300740001926698,
      "spearman_c0_abs_error": 0.02716648329885657,
      "spearman_c0_residual": -0.028036219327441998,
      "train_identity_mean": 58.8212392482178,
      "train_identity_n": 284,
      "train_n": 10180,
      "val_identities_with_any_missing": 8,
      "val_identity_mean": 47.75703703883104,
      "val_identity_n": 32,
      "val_n": 2222,
      "wasserstein": 9.286985918631153
    },
    "da_median_distance": {
      "smd": -0.20935273887236064,
      "spearman_acceptor_similarity": 0.10504370541616263,
      "spearman_c0_abs_error": 0.013482820682981917,
      "spearman_c0_residual": -0.04302939813893454,
      "train_identity_mean": 16.010007280179714,
      "train_identity_n": 284,
      "train_n": 10180,
      "val_identities_with_any_missing": 8,
      "val_identity_mean": 15.036199479923567,
      "val_identity_n": 32,
      "val_n": 2222,
      "wasserstein": 0.9159816760738773
    },
    "da_min_distance": {
      "smd": 0.2864409500587326,
      "spearman_acceptor_similarity": 0.1620711736604944,
      "spearman_c0_abs_error": -0.05502878797304853,
      "spearman_c0_residual": -0.05738130754818541,
      "train_identity_mean": 1.459795596044256,
      "train_identity_n": 284,
      "train_n": 10180,
      "val_identities_with_any_missing": 8,
      "val_identity_mean": 1.469233006965978,
      "val_identity_n": 32,
      "val_n": 2222,
      "wasserstein": 0.0076982812765689
    },
    "da_q25_distance": {
      "smd": -0.32910918107072357,
      "spearman_acceptor_similarity": 0.19228887795544367,
      "spearman_c0_abs_error": 0.019456555225198794,
      "spearman_c0_residual": -0.03723193293942354,
      "train_identity_mean": 11.664856112960898,
      "train_identity_n": 284,
      "train_n": 10180,
      "val_identities_with_any_missing": 8,
      "val_identity_mean": 10.574666028749107,
      "val_identity_n": 32,
      "val_n": 2222,
      "wasserstein": 0.9602492250084385
    },
    "da_q75_distance": {
      "smd": -0.141033567343871,
      "spearman_acceptor_similarity": 0.10168053932070278,
      "spearman_c0_abs_error": -0.00519371953892832,
      "spearman_c0_residual": -0.04213217122560616,
      "train_identity_mean": 20.717101131125496,
      "train_identity_n": 284,
      "train_n": 10180,
      "val_identities_with_any_missing": 8,
      "val_identity_mean": 19.848406263391432,
      "val_identity_n": 32,
      "val_n": 2222,
      "wasserstein": 0.9401643812754156
    },
    "donor_interface_atoms_4A": {
      "smd": -0.046502476032294834,
      "spearman_acceptor_similarity": -0.001267817328814598,
      "spearman_c0_abs_error": 0.01650520632898815,
      "spearman_c0_residual": -0.020206433602234824,
      "train_identity_mean": 6.705264606343096,
      "train_identity_n": 284,
      "train_n": 10180,
      "val_identities_with_any_missing": 8,
      "val_identity_mean": 6.657615728984032,
      "val_identity_n": 32,
      "val_n": 2222,
      "wasserstein": 0.2896143052419187
    },
    "identity_power": {
      "train_acceptor_identities": 284,
      "validation_acceptor_identities": 32
    },
    "unknown_acceptor_min_distance": {
      "smd": 0.31369110481361323,
      "spearman_acceptor_similarity": -0.4734677439321473,
      "spearman_c0_abs_error": 0.20617760617760622,
      "spearman_c0_residual": 0.12226512226512229,
      "train_identity_mean": 3.7958886260979994,
      "train_identity_n": 249,
      "train_n": 658,
      "val_identities_with_any_missing": 32,
      "val_identity_mean": 5.142124311670658,
      "val_identity_n": 13,
      "val_n": 36,
      "wasserstein": 1.2132760217475063
    },
    "unknown_donor_min_distance": {
      "smd": -0.2283536911129702,
      "spearman_acceptor_similarity": 0.06021555121067955,
      "spearman_c0_abs_error": -0.19762845849802374,
      "spearman_c0_residual": -0.40711462450592883,
      "train_identity_mean": 1.5156345697832412,
      "train_identity_n": 205,
      "train_n": 295,
      "val_identities_with_any_missing": 32,
      "val_identity_mean": 1.4685440069058584,
      "val_identity_n": 13,
      "val_n": 23,
      "wasserstein": 0.2243851773940816
    }
  }
}
